{"search":[{"#":1,"id":589,"order":null,"parents_id":[589],"parents_title":["1"],"selectedIdx":[4],"selectedPath":[{"#":1,"id":589,"order":null,"parents_id":[589],"parents_title":["1"],"selectedIdx":[4],"selectedPath":[],"title":"1"}],"title":"1"},{"#":2,"id":596,"order":null,"parents_id":[589,596],"parents_title":["1","2"],"selectedIdx":[4,0],"selectedPath":[{"#":1,"id":589,"order":null,"parents_id":[589],"parents_title":["1"],"selectedIdx":[4],"selectedPath":[{"#":1,"id":589,"order":null,"parents_id":[589],"parents_title":["1"],"selectedIdx":[4],"selectedPath":[],"title":"1"}],"title":"1"},{"#":2,"id":596,"order":null,"parents_id":[589,596],"parents_title":["1","2"],"selectedIdx":[4,0],"selectedPath":[{"#":1,"id":589,"order":null,"parents_id":[589],"parents_title":["1"],"selectedIdx":[4],"selectedPath":[{"#":1,"id":589,"order":null,"parents_id":[589],"parents_title":["1"],"selectedIdx":[4],"selectedPath":[],"title":"1"}],"title":"1"}],"title":"2"}],"title":"2"},{"#":3,"id":603,"order":null,"parents_id":[603],"parents_title":["11"],"selectedIdx":[5],"selectedPath":[{"#":3,"id":603,"order":null,"parents_id":[603],"parents_title":["11"],"selectedIdx":[5],"selectedPath":[],"title":"11"}],"title":"11"},{"#":4,"id":570,"order":null,"parents_id":[570],"parents_title":["45"],"selectedIdx":[2],"selectedPath":[{"#":4,"id":570,"order":null,"parents_id":[570],"parents_title":["45"],"selectedIdx":[2],"selectedPath":[],"title":"45"}],"title":"45"},{"#":5,"id":575,"order":null,"parents_id":[575],"parents_title":["56"],"selectedIdx":[3],"selectedPath":[{"#":5,"id":575,"order":null,"parents_id":[575],"parents_title":["56"],"selectedIdx":[3],"selectedPath":[],"title":"56"}],"title":"56"},{"#":6,"id":611,"order":null,"parents_id":[611],"parents_title":["банк"],"selectedIdx":[6],"selectedPath":[{"#":6,"id":611,"order":null,"parents_id":[611],"parents_title":["банк"],"selectedIdx":[6],"selectedPath":[],"title":"банк"}],"title":"банк"},{"#":7,"id":613,"order":null,"parents_id":[611,613],"parents_title":["банк","комиссия"],"selectedIdx":[6,0],"selectedPath":[{"#":6,"id":611,"order":null,"parents_id":[611],"parents_title":["банк"],"selectedIdx":[6],"title":"банк"},{"#":7,"id":613,"order":null,"parents_id":[611,613],"parents_title":["банк","комиссия"],"selectedIdx":[6,0],"selectedPath":[{"#":6,"id":611,"order":null,"parents_id":[611],"parents_title":["банк"],"selectedIdx":[6],"title":"банк"}],"title":"комиссия"}],"title":"комиссия"},{"#":8,"id":534,"order":null,"parents_id":[534],"parents_title":["ввод остатка"],"selectedIdx":[0],"selectedPath":[{"#":8,"id":534,"order":null,"parents_id":[534],"parents_title":["ввод остатка"],"selectedIdx":[0],"selectedPath":[],"title":"ввод остатка"}],"title":"ввод остатка"},{"#":9,"id":618,"order":null,"parents_id":[618],"parents_title":["инко"],"selectedIdx":[7],"selectedPath":[{"#":9,"id":618,"order":null,"parents_id":[618],"parents_title":["инко"],"selectedIdx":[7],"selectedPath":[],"title":"инко"}],"title":"инко"},{"#":10,"id":541,"order":null,"parents_id":[541],"parents_title":["пермблаг-во"],"selectedIdx":[1],"selectedPath":[{"#":10,"id":541,"order":null,"parents_id":[541],"parents_title":["пермблаг-во"],"selectedIdx":[1],"selectedPath":[],"title":"пермблаг-во"}],"title":"пермблаг-во"},{"#":11,"id":543,"order":null,"parents_id":[541,543],"parents_title":["пермблаг-во","берег"],"selectedIdx":[1,0],"selectedPath":[{"#":10,"id":541,"order":null,"parents_id":[541],"parents_title":["пермблаг-во"],"selectedIdx":[1],"title":"пермблаг-во"},{"#":11,"id":543,"order":null,"parents_id":[541,543],"parents_title":["пермблаг-во","берег"],"selectedIdx":[1,0],"selectedPath":[{"#":10,"id":541,"order":null,"parents_id":[541],"parents_title":["пермблаг-во"],"selectedIdx":[1],"title":"пермблаг-во"}],"title":"берег"}],"title":"берег"}],"tree":[{"_childs_ids":null,"childs":[],"id":534,"order":null,"parent":3,"title":"ввод остатка"},{"_childs_ids":[543],"childs":[{"_childs_ids":null,"childs":[],"id":543,"order":null,"parent":541,"title":"берег"}],"id":541,"order":null,"parent":3,"title":"пермблаг-во"},{"_childs_ids":null,"childs":[],"id":570,"order":null,"parent":3,"title":"45"},{"_childs_ids":null,"childs":[],"id":575,"order":null,"parent":3,"title":"56"},{"_childs_ids":[596],"childs":[{"_childs_ids":null,"childs":[],"id":596,"order":null,"parent":589,"title":"2"}],"id":589,"order":null,"parent":3,"title":"1"},{"_childs_ids":null,"childs":[],"id":603,"order":null,"parent":3,"title":"11"},{"_childs_ids":[613],"childs":[{"_childs_ids":null,"childs":[],"id":613,"order":null,"parent":611,"title":"комиссия"}],"id":611,"order":null,"parent":3,"title":"банк"},{"_childs_ids":null,"childs":[],"id":618,"order":null,"parent":3,"title":"инко"}]}